{
    "category": "timeSeries", 
    "data": {
        "col1": {
            "label": "Disabled-worker beneficiaries", 
            "series": [
                8993, 
                9088, 
                9194, 
                9293, 
                9349, 
                9457, 
                9552, 
                9635, 
                9713, 
                9790, 
                9904, 
                9854, 
                9817, 
                9790, 
                9771, 
                9761, 
                9791, 
                9848, 
                9920, 
                9988, 
                10046, 
                10084, 
                10151, 
                10254, 
                10391, 
                10528, 
                10673, 
                10818, 
                10947, 
                11078, 
                11192, 
                11283, 
                11384, 
                11473, 
                11577, 
                11678, 
                11767, 
                11858, 
                11944, 
                12012, 
                12062, 
                12090, 
                12124, 
                12161, 
                12210, 
                12270, 
                12337, 
                12408, 
                12482, 
                12547, 
                12612, 
                12668, 
                12737, 
                12805, 
                12866, 
                12925, 
                12978, 
                13015, 
                13044, 
                13082, 
                13151, 
                13240, 
                13354, 
                13478, 
                13613, 
                13753, 
                13892, 
                14022, 
                14140, 
                14246, 
                14339, 
                14420, 
                14488, 
                14545, 
                14594
            ], 
            "type": "numberThousand"
        }, 
        "col2": {
            "label": "Auxiliary beneficiaries :: Spouse", 
            "series": [
                139, 
                137, 
                135, 
                134, 
                139, 
                144, 
                147, 
                148, 
                149, 
                153, 
                161, 
                164, 
                164, 
                165, 
                166, 
                171, 
                175, 
                177, 
                181, 
                184, 
                188, 
                188, 
                188, 
                189, 
                193, 
                198, 
                202, 
                204, 
                206, 
                207, 
                211, 
                212, 
                211, 
                210, 
                211, 
                214, 
                216, 
                217, 
                219, 
                220, 
                221, 
                221, 
                221, 
                221, 
                222, 
                223, 
                225, 
                227, 
                229, 
                232, 
                235, 
                237, 
                239, 
                242, 
                243, 
                244, 
                245, 
                245, 
                245, 
                245, 
                246, 
                248, 
                250, 
                253, 
                256, 
                260, 
                263, 
                265, 
                268, 
                270, 
                272, 
                273, 
                274, 
                275, 
                275
            ], 
            "type": "number"
        }, 
        "col3": {
            "label": "Auxiliary beneficiaries :: Child", 
            "series": [
                1739, 
                1736, 
                1743, 
                1754, 
                1764, 
                1769, 
                1777, 
                1786, 
                1793, 
                1800, 
                1823, 
                1850, 
                1883, 
                1923, 
                1966, 
                2011, 
                2058, 
                2109, 
                2159, 
                2208, 
                2241, 
                2272, 
                2299, 
                2324, 
                2346, 
                2363, 
                2380, 
                2396, 
                2412, 
                2429, 
                2444, 
                2458, 
                2471, 
                2484, 
                2497, 
                2509, 
                2521, 
                2533, 
                2544, 
                2556, 
                2568, 
                2580, 
                2593, 
                2607, 
                2622, 
                2637, 
                2654, 
                2672, 
                2690, 
                2709, 
                2729, 
                2748, 
                2767, 
                2786, 
                2805, 
                2822, 
                2839, 
                2855, 
                2870, 
                2884, 
                2898, 
                2911, 
                2924, 
                2938, 
                2951, 
                2965, 
                2978, 
                2992, 
                3006, 
                3020, 
                3034, 
                3049, 
                3064, 
                3079, 
                3094
            ], 
            "type": "number"
        }, 
        "col4": {
            "label": "Total beneficiaries", 
            "series": [
                10871, 
                10961, 
                11072, 
                11181, 
                11252, 
                11370, 
                11475, 
                11569, 
                11656, 
                11742, 
                11888, 
                11868, 
                11864, 
                11877, 
                11904, 
                11943, 
                12023, 
                12134, 
                12260, 
                12381, 
                12475, 
                12543, 
                12638, 
                12768, 
                12929, 
                13089, 
                13255, 
                13419, 
                13565, 
                13714, 
                13847, 
                13953, 
                14067, 
                14167, 
                14284, 
                14400, 
                14503, 
                14608, 
                14707, 
                14788, 
                14851, 
                14891, 
                14938, 
                14989, 
                15054, 
                15130, 
                15216, 
                15307, 
                15402, 
                15488, 
                15575, 
                15653, 
                15743, 
                15833, 
                15914, 
                15991, 
                16062, 
                16115, 
                16158, 
                16210, 
                16295, 
                16399, 
                16528, 
                16668, 
                16820, 
                16977, 
                17133, 
                17279, 
                17414, 
                17536, 
                17645, 
                17741, 
                17825, 
                17899, 
                17963
            ], 
            "type": "numberThousand"
        }, 
        "col5": {
            "label": "Disability prevalence rates :: Gross", 
            "series": [
                59, 
                59, 
                60, 
                60, 
                60, 
                61, 
                61, 
                61, 
                61, 
                62, 
                61, 
                61, 
                60, 
                60, 
                59, 
                59, 
                59, 
                59, 
                59, 
                59, 
                59, 
                59, 
                60, 
                60, 
                60, 
                61, 
                61, 
                62, 
                62, 
                62, 
                63, 
                63, 
                63, 
                63, 
                64, 
                64, 
                64, 
                64, 
                64, 
                65, 
                65, 
                65, 
                64, 
                64, 
                64, 
                65, 
                65, 
                65, 
                65, 
                65, 
                65, 
                65, 
                65, 
                65, 
                65, 
                65, 
                65, 
                65, 
                65, 
                65, 
                65, 
                65, 
                65, 
                65, 
                66, 
                66, 
                66, 
                66, 
                67, 
                67, 
                67, 
                67, 
                67, 
                67, 
                67
            ], 
            "type": "number"
        }, 
        "col6": {
            "label": "Disability prevalence rates :: Age-sex adjusted", 
            "series": [
                45, 
                45, 
                45, 
                45, 
                45, 
                45, 
                45, 
                45, 
                45, 
                45, 
                45, 
                45, 
                45, 
                45, 
                45, 
                45, 
                45, 
                45, 
                45, 
                45, 
                45, 
                45, 
                46, 
                46, 
                46, 
                46, 
                46, 
                46, 
                47, 
                47, 
                47, 
                47, 
                47, 
                47, 
                47, 
                48, 
                48, 
                48, 
                48, 
                48, 
                48, 
                48, 
                48, 
                48, 
                48, 
                48, 
                49, 
                49, 
                49, 
                49, 
                49, 
                49, 
                49, 
                49, 
                49, 
                49, 
                49, 
                49, 
                49, 
                49, 
                49, 
                49, 
                49, 
                49, 
                49, 
                49, 
                49, 
                49, 
                50, 
                50, 
                50, 
                50, 
                50, 
                50, 
                50
            ], 
            "type": "number"
        }, 
        "years": {
            "label": "Calendar year", 
            "series": [
                2016, 
                2017, 
                2018, 
                2019, 
                2020, 
                2021, 
                2022, 
                2023, 
                2024, 
                2025, 
                2026, 
                2027, 
                2028, 
                2029, 
                2030, 
                2031, 
                2032, 
                2033, 
                2034, 
                2035, 
                2036, 
                2037, 
                2038, 
                2039, 
                2040, 
                2041, 
                2042, 
                2043, 
                2044, 
                2045, 
                2046, 
                2047, 
                2048, 
                2049, 
                2050, 
                2051, 
                2052, 
                2053, 
                2054, 
                2055, 
                2056, 
                2057, 
                2058, 
                2059, 
                2060, 
                2061, 
                2062, 
                2063, 
                2064, 
                2065, 
                2066, 
                2067, 
                2068, 
                2069, 
                2070, 
                2071, 
                2072, 
                2073, 
                2074, 
                2075, 
                2076, 
                2077, 
                2078, 
                2079, 
                2080, 
                2081, 
                2082, 
                2083, 
                2084, 
                2085, 
                2086, 
                2087, 
                2088, 
                2089, 
                2090
            ], 
            "type": "year"
        }
    }, 
    "footnotes": [
        {
            "content": "Adjusted to the age-sex distribution of the insured population for the year 2000. Note: Totals do not necessarily equal the sums of rounded components.", 
            "symbol": "a", 
            "type": "footnote"
        }
    ], 
    "html": {
        "body": "<tbody><tr><td class=\"col0\">2016</td><td></td><td class=\"col1\">8,993</td><td></td><td class=\"col2\">139</td><td></td><td class=\"col3\">1,739</td><td></td><td class=\"col4\">10,871</td><td></td><td class=\"col5\">59</td><td></td><td class=\"col6\">45</td></tr><tr><td class=\"col0\">2017</td><td></td><td class=\"col1\">9,088</td><td></td><td class=\"col2\">137</td><td></td><td class=\"col3\">1,736</td><td></td><td class=\"col4\">10,961</td><td></td><td class=\"col5\">59</td><td></td><td class=\"col6\">45</td></tr><tr><td class=\"col0\">2018</td><td></td><td class=\"col1\">9,194</td><td></td><td class=\"col2\">135</td><td></td><td class=\"col3\">1,743</td><td></td><td class=\"col4\">11,072</td><td></td><td class=\"col5\">60</td><td></td><td class=\"col6\">45</td></tr><tr><td class=\"col0\">2019</td><td></td><td class=\"col1\">9,293</td><td></td><td class=\"col2\">134</td><td></td><td class=\"col3\">1,754</td><td></td><td class=\"col4\">11,181</td><td></td><td class=\"col5\">60</td><td></td><td class=\"col6\">45</td></tr><tr><td class=\"col0\">2020</td><td></td><td class=\"col1\">9,349</td><td></td><td class=\"col2\">139</td><td></td><td class=\"col3\">1,764</td><td></td><td class=\"col4\">11,252</td><td></td><td class=\"col5\">60</td><td></td><td class=\"col6\">45</td></tr><tr><td class=\"col0\">2021</td><td></td><td class=\"col1\">9,457</td><td></td><td class=\"col2\">144</td><td></td><td class=\"col3\">1,769</td><td></td><td class=\"col4\">11,370</td><td></td><td class=\"col5\">61</td><td></td><td class=\"col6\">45</td></tr><tr><td class=\"col0\">2022</td><td></td><td class=\"col1\">9,552</td><td></td><td class=\"col2\">147</td><td></td><td class=\"col3\">1,777</td><td></td><td class=\"col4\">11,475</td><td></td><td class=\"col5\">61</td><td></td><td class=\"col6\">45</td></tr><tr><td class=\"col0\">2023</td><td></td><td class=\"col1\">9,635</td><td></td><td class=\"col2\">148</td><td></td><td class=\"col3\">1,786</td><td></td><td class=\"col4\">11,569</td><td></td><td class=\"col5\">61</td><td></td><td class=\"col6\">45</td></tr><tr><td class=\"col0\">2024</td><td></td><td class=\"col1\">9,713</td><td></td><td class=\"col2\">149</td><td></td><td class=\"col3\">1,793</td><td></td><td class=\"col4\">11,656</td><td></td><td class=\"col5\">61</td><td></td><td class=\"col6\">45</td></tr><tr><td class=\"col0\">2025</td><td></td><td class=\"col1\">9,790</td><td></td><td class=\"col2\">153</td><td></td><td class=\"col3\">1,800</td><td></td><td class=\"col4\">11,742</td><td></td><td class=\"col5\">62</td><td></td><td class=\"col6\">45</td></tr><tr><td class=\"col0\">2026</td><td></td><td class=\"col1\">9,904</td><td></td><td class=\"col2\">161</td><td></td><td class=\"col3\">1,823</td><td></td><td class=\"col4\">11,888</td><td></td><td class=\"col5\">61</td><td></td><td class=\"col6\">45</td></tr><tr><td class=\"col0\">2027</td><td></td><td class=\"col1\">9,854</td><td></td><td class=\"col2\">164</td><td></td><td class=\"col3\">1,850</td><td></td><td class=\"col4\">11,868</td><td></td><td class=\"col5\">61</td><td></td><td class=\"col6\">45</td></tr><tr><td class=\"col0\">2028</td><td></td><td class=\"col1\">9,817</td><td></td><td class=\"col2\">164</td><td></td><td class=\"col3\">1,883</td><td></td><td class=\"col4\">11,864</td><td></td><td class=\"col5\">60</td><td></td><td class=\"col6\">45</td></tr><tr><td class=\"col0\">2029</td><td></td><td class=\"col1\">9,790</td><td></td><td class=\"col2\">165</td><td></td><td class=\"col3\">1,923</td><td></td><td class=\"col4\">11,877</td><td></td><td class=\"col5\">60</td><td></td><td class=\"col6\">45</td></tr><tr><td class=\"col0\">2030</td><td></td><td class=\"col1\">9,771</td><td></td><td class=\"col2\">166</td><td></td><td class=\"col3\">1,966</td><td></td><td class=\"col4\">11,904</td><td></td><td class=\"col5\">59</td><td></td><td class=\"col6\">45</td></tr><tr><td class=\"col0\">2031</td><td></td><td class=\"col1\">9,761</td><td></td><td class=\"col2\">171</td><td></td><td class=\"col3\">2,011</td><td></td><td class=\"col4\">11,943</td><td></td><td class=\"col5\">59</td><td></td><td class=\"col6\">45</td></tr><tr><td class=\"col0\">2032</td><td></td><td class=\"col1\">9,791</td><td></td><td class=\"col2\">175</td><td></td><td class=\"col3\">2,058</td><td></td><td class=\"col4\">12,023</td><td></td><td class=\"col5\">59</td><td></td><td class=\"col6\">45</td></tr><tr><td class=\"col0\">2033</td><td></td><td class=\"col1\">9,848</td><td></td><td class=\"col2\">177</td><td></td><td class=\"col3\">2,109</td><td></td><td class=\"col4\">12,134</td><td></td><td class=\"col5\">59</td><td></td><td class=\"col6\">45</td></tr><tr><td class=\"col0\">2034</td><td></td><td class=\"col1\">9,920</td><td></td><td class=\"col2\">181</td><td></td><td class=\"col3\">2,159</td><td></td><td class=\"col4\">12,260</td><td></td><td class=\"col5\">59</td><td></td><td class=\"col6\">45</td></tr><tr><td class=\"col0\">2035</td><td></td><td class=\"col1\">9,988</td><td></td><td class=\"col2\">184</td><td></td><td class=\"col3\">2,208</td><td></td><td class=\"col4\">12,381</td><td></td><td class=\"col5\">59</td><td></td><td class=\"col6\">45</td></tr><tr><td class=\"col0\">2036</td><td></td><td class=\"col1\">10,046</td><td></td><td class=\"col2\">188</td><td></td><td class=\"col3\">2,241</td><td></td><td class=\"col4\">12,475</td><td></td><td class=\"col5\">59</td><td></td><td class=\"col6\">45</td></tr><tr><td class=\"col0\">2037</td><td></td><td class=\"col1\">10,084</td><td></td><td class=\"col2\">188</td><td></td><td class=\"col3\">2,272</td><td></td><td class=\"col4\">12,543</td><td></td><td class=\"col5\">59</td><td></td><td class=\"col6\">45</td></tr><tr><td class=\"col0\">2038</td><td></td><td class=\"col1\">10,151</td><td></td><td class=\"col2\">188</td><td></td><td class=\"col3\">2,299</td><td></td><td class=\"col4\">12,638</td><td></td><td class=\"col5\">60</td><td></td><td class=\"col6\">46</td></tr><tr><td class=\"col0\">2039</td><td></td><td class=\"col1\">10,254</td><td></td><td class=\"col2\">189</td><td></td><td class=\"col3\">2,324</td><td></td><td class=\"col4\">12,768</td><td></td><td class=\"col5\">60</td><td></td><td class=\"col6\">46</td></tr><tr><td class=\"col0\">2040</td><td></td><td class=\"col1\">10,391</td><td></td><td class=\"col2\">193</td><td></td><td class=\"col3\">2,346</td><td></td><td class=\"col4\">12,929</td><td></td><td class=\"col5\">60</td><td></td><td class=\"col6\">46</td></tr><tr><td class=\"col0\">2041</td><td></td><td class=\"col1\">10,528</td><td></td><td class=\"col2\">198</td><td></td><td class=\"col3\">2,363</td><td></td><td class=\"col4\">13,089</td><td></td><td class=\"col5\">61</td><td></td><td class=\"col6\">46</td></tr><tr><td class=\"col0\">2042</td><td></td><td class=\"col1\">10,673</td><td></td><td class=\"col2\">202</td><td></td><td class=\"col3\">2,380</td><td></td><td class=\"col4\">13,255</td><td></td><td class=\"col5\">61</td><td></td><td class=\"col6\">46</td></tr><tr><td class=\"col0\">2043</td><td></td><td class=\"col1\">10,818</td><td></td><td class=\"col2\">204</td><td></td><td class=\"col3\">2,396</td><td></td><td class=\"col4\">13,419</td><td></td><td class=\"col5\">62</td><td></td><td class=\"col6\">46</td></tr><tr><td class=\"col0\">2044</td><td></td><td class=\"col1\">10,947</td><td></td><td class=\"col2\">206</td><td></td><td class=\"col3\">2,412</td><td></td><td class=\"col4\">13,565</td><td></td><td class=\"col5\">62</td><td></td><td class=\"col6\">47</td></tr><tr><td class=\"col0\">2045</td><td></td><td class=\"col1\">11,078</td><td></td><td class=\"col2\">207</td><td></td><td class=\"col3\">2,429</td><td></td><td class=\"col4\">13,714</td><td></td><td class=\"col5\">62</td><td></td><td class=\"col6\">47</td></tr><tr><td class=\"col0\">2046</td><td></td><td class=\"col1\">11,192</td><td></td><td class=\"col2\">211</td><td></td><td class=\"col3\">2,444</td><td></td><td class=\"col4\">13,847</td><td></td><td class=\"col5\">63</td><td></td><td class=\"col6\">47</td></tr><tr><td class=\"col0\">2047</td><td></td><td class=\"col1\">11,283</td><td></td><td class=\"col2\">212</td><td></td><td class=\"col3\">2,458</td><td></td><td class=\"col4\">13,953</td><td></td><td class=\"col5\">63</td><td></td><td class=\"col6\">47</td></tr><tr><td class=\"col0\">2048</td><td></td><td class=\"col1\">11,384</td><td></td><td class=\"col2\">211</td><td></td><td class=\"col3\">2,471</td><td></td><td class=\"col4\">14,067</td><td></td><td class=\"col5\">63</td><td></td><td class=\"col6\">47</td></tr><tr><td class=\"col0\">2049</td><td></td><td class=\"col1\">11,473</td><td></td><td class=\"col2\">210</td><td></td><td class=\"col3\">2,484</td><td></td><td class=\"col4\">14,167</td><td></td><td class=\"col5\">63</td><td></td><td class=\"col6\">47</td></tr><tr><td class=\"col0\">2050</td><td></td><td class=\"col1\">11,577</td><td></td><td class=\"col2\">211</td><td></td><td class=\"col3\">2,497</td><td></td><td class=\"col4\">14,284</td><td></td><td class=\"col5\">64</td><td></td><td class=\"col6\">47</td></tr><tr><td class=\"col0\">2051</td><td></td><td class=\"col1\">11,678</td><td></td><td class=\"col2\">214</td><td></td><td class=\"col3\">2,509</td><td></td><td class=\"col4\">14,400</td><td></td><td class=\"col5\">64</td><td></td><td class=\"col6\">48</td></tr><tr><td class=\"col0\">2052</td><td></td><td class=\"col1\">11,767</td><td></td><td class=\"col2\">216</td><td></td><td class=\"col3\">2,521</td><td></td><td class=\"col4\">14,503</td><td></td><td class=\"col5\">64</td><td></td><td class=\"col6\">48</td></tr><tr><td class=\"col0\">2053</td><td></td><td class=\"col1\">11,858</td><td></td><td class=\"col2\">217</td><td></td><td class=\"col3\">2,533</td><td></td><td class=\"col4\">14,608</td><td></td><td class=\"col5\">64</td><td></td><td class=\"col6\">48</td></tr><tr><td class=\"col0\">2054</td><td></td><td class=\"col1\">11,944</td><td></td><td class=\"col2\">219</td><td></td><td class=\"col3\">2,544</td><td></td><td class=\"col4\">14,707</td><td></td><td class=\"col5\">64</td><td></td><td class=\"col6\">48</td></tr><tr><td class=\"col0\">2055</td><td></td><td class=\"col1\">12,012</td><td></td><td class=\"col2\">220</td><td></td><td class=\"col3\">2,556</td><td></td><td class=\"col4\">14,788</td><td></td><td class=\"col5\">65</td><td></td><td class=\"col6\">48</td></tr><tr><td class=\"col0\">2056</td><td></td><td class=\"col1\">12,062</td><td></td><td class=\"col2\">221</td><td></td><td class=\"col3\">2,568</td><td></td><td class=\"col4\">14,851</td><td></td><td class=\"col5\">65</td><td></td><td class=\"col6\">48</td></tr><tr><td class=\"col0\">2057</td><td></td><td class=\"col1\">12,090</td><td></td><td class=\"col2\">221</td><td></td><td class=\"col3\">2,580</td><td></td><td class=\"col4\">14,891</td><td></td><td class=\"col5\">65</td><td></td><td class=\"col6\">48</td></tr><tr><td class=\"col0\">2058</td><td></td><td class=\"col1\">12,124</td><td></td><td class=\"col2\">221</td><td></td><td class=\"col3\">2,593</td><td></td><td class=\"col4\">14,938</td><td></td><td class=\"col5\">64</td><td></td><td class=\"col6\">48</td></tr><tr><td class=\"col0\">2059</td><td></td><td class=\"col1\">12,161</td><td></td><td class=\"col2\">221</td><td></td><td class=\"col3\">2,607</td><td></td><td class=\"col4\">14,989</td><td></td><td class=\"col5\">64</td><td></td><td class=\"col6\">48</td></tr><tr><td class=\"col0\">2060</td><td></td><td class=\"col1\">12,210</td><td></td><td class=\"col2\">222</td><td></td><td class=\"col3\">2,622</td><td></td><td class=\"col4\">15,054</td><td></td><td class=\"col5\">64</td><td></td><td class=\"col6\">48</td></tr><tr><td class=\"col0\">2061</td><td></td><td class=\"col1\">12,270</td><td></td><td class=\"col2\">223</td><td></td><td class=\"col3\">2,637</td><td></td><td class=\"col4\">15,130</td><td></td><td class=\"col5\">65</td><td></td><td class=\"col6\">48</td></tr><tr><td class=\"col0\">2062</td><td></td><td class=\"col1\">12,337</td><td></td><td class=\"col2\">225</td><td></td><td class=\"col3\">2,654</td><td></td><td class=\"col4\">15,216</td><td></td><td class=\"col5\">65</td><td></td><td class=\"col6\">49</td></tr><tr><td class=\"col0\">2063</td><td></td><td class=\"col1\">12,408</td><td></td><td class=\"col2\">227</td><td></td><td class=\"col3\">2,672</td><td></td><td class=\"col4\">15,307</td><td></td><td class=\"col5\">65</td><td></td><td class=\"col6\">49</td></tr><tr><td class=\"col0\">2064</td><td></td><td class=\"col1\">12,482</td><td></td><td class=\"col2\">229</td><td></td><td class=\"col3\">2,690</td><td></td><td class=\"col4\">15,402</td><td></td><td class=\"col5\">65</td><td></td><td class=\"col6\">49</td></tr><tr><td class=\"col0\">2065</td><td></td><td class=\"col1\">12,547</td><td></td><td class=\"col2\">232</td><td></td><td class=\"col3\">2,709</td><td></td><td class=\"col4\">15,488</td><td></td><td class=\"col5\">65</td><td></td><td class=\"col6\">49</td></tr><tr><td class=\"col0\">2066</td><td></td><td class=\"col1\">12,612</td><td></td><td class=\"col2\">235</td><td></td><td class=\"col3\">2,729</td><td></td><td class=\"col4\">15,575</td><td></td><td class=\"col5\">65</td><td></td><td class=\"col6\">49</td></tr><tr><td class=\"col0\">2067</td><td></td><td class=\"col1\">12,668</td><td></td><td class=\"col2\">237</td><td></td><td class=\"col3\">2,748</td><td></td><td class=\"col4\">15,653</td><td></td><td class=\"col5\">65</td><td></td><td class=\"col6\">49</td></tr><tr><td class=\"col0\">2068</td><td></td><td class=\"col1\">12,737</td><td></td><td class=\"col2\">239</td><td></td><td class=\"col3\">2,767</td><td></td><td class=\"col4\">15,743</td><td></td><td class=\"col5\">65</td><td></td><td class=\"col6\">49</td></tr><tr><td class=\"col0\">2069</td><td></td><td class=\"col1\">12,805</td><td></td><td class=\"col2\">242</td><td></td><td class=\"col3\">2,786</td><td></td><td class=\"col4\">15,833</td><td></td><td class=\"col5\">65</td><td></td><td class=\"col6\">49</td></tr><tr><td class=\"col0\">2070</td><td></td><td class=\"col1\">12,866</td><td></td><td class=\"col2\">243</td><td></td><td class=\"col3\">2,805</td><td></td><td class=\"col4\">15,914</td><td></td><td class=\"col5\">65</td><td></td><td class=\"col6\">49</td></tr><tr><td class=\"col0\">2071</td><td></td><td class=\"col1\">12,925</td><td></td><td class=\"col2\">244</td><td></td><td class=\"col3\">2,822</td><td></td><td class=\"col4\">15,991</td><td></td><td class=\"col5\">65</td><td></td><td class=\"col6\">49</td></tr><tr><td class=\"col0\">2072</td><td></td><td class=\"col1\">12,978</td><td></td><td class=\"col2\">245</td><td></td><td class=\"col3\">2,839</td><td></td><td class=\"col4\">16,062</td><td></td><td class=\"col5\">65</td><td></td><td class=\"col6\">49</td></tr><tr><td class=\"col0\">2073</td><td></td><td class=\"col1\">13,015</td><td></td><td class=\"col2\">245</td><td></td><td class=\"col3\">2,855</td><td></td><td class=\"col4\">16,115</td><td></td><td class=\"col5\">65</td><td></td><td class=\"col6\">49</td></tr><tr><td class=\"col0\">2074</td><td></td><td class=\"col1\">13,044</td><td></td><td class=\"col2\">245</td><td></td><td class=\"col3\">2,870</td><td></td><td class=\"col4\">16,158</td><td></td><td class=\"col5\">65</td><td></td><td class=\"col6\">49</td></tr><tr><td class=\"col0\">2075</td><td></td><td class=\"col1\">13,082</td><td></td><td class=\"col2\">245</td><td></td><td class=\"col3\">2,884</td><td></td><td class=\"col4\">16,210</td><td></td><td class=\"col5\">65</td><td></td><td class=\"col6\">49</td></tr><tr><td class=\"col0\">2076</td><td></td><td class=\"col1\">13,151</td><td></td><td class=\"col2\">246</td><td></td><td class=\"col3\">2,898</td><td></td><td class=\"col4\">16,295</td><td></td><td class=\"col5\">65</td><td></td><td class=\"col6\">49</td></tr><tr><td class=\"col0\">2077</td><td></td><td class=\"col1\">13,240</td><td></td><td class=\"col2\">248</td><td></td><td class=\"col3\">2,911</td><td></td><td class=\"col4\">16,399</td><td></td><td class=\"col5\">65</td><td></td><td class=\"col6\">49</td></tr><tr><td class=\"col0\">2078</td><td></td><td class=\"col1\">13,354</td><td></td><td class=\"col2\">250</td><td></td><td class=\"col3\">2,924</td><td></td><td class=\"col4\">16,528</td><td></td><td class=\"col5\">65</td><td></td><td class=\"col6\">49</td></tr><tr><td class=\"col0\">2079</td><td></td><td class=\"col1\">13,478</td><td></td><td class=\"col2\">253</td><td></td><td class=\"col3\">2,938</td><td></td><td class=\"col4\">16,668</td><td></td><td class=\"col5\">65</td><td></td><td class=\"col6\">49</td></tr><tr><td class=\"col0\">2080</td><td></td><td class=\"col1\">13,613</td><td></td><td class=\"col2\">256</td><td></td><td class=\"col3\">2,951</td><td></td><td class=\"col4\">16,820</td><td></td><td class=\"col5\">66</td><td></td><td class=\"col6\">49</td></tr><tr><td class=\"col0\">2081</td><td></td><td class=\"col1\">13,753</td><td></td><td class=\"col2\">260</td><td></td><td class=\"col3\">2,965</td><td></td><td class=\"col4\">16,977</td><td></td><td class=\"col5\">66</td><td></td><td class=\"col6\">49</td></tr><tr><td class=\"col0\">2082</td><td></td><td class=\"col1\">13,892</td><td></td><td class=\"col2\">263</td><td></td><td class=\"col3\">2,978</td><td></td><td class=\"col4\">17,133</td><td></td><td class=\"col5\">66</td><td></td><td class=\"col6\">49</td></tr><tr><td class=\"col0\">2083</td><td></td><td class=\"col1\">14,022</td><td></td><td class=\"col2\">265</td><td></td><td class=\"col3\">2,992</td><td></td><td class=\"col4\">17,279</td><td></td><td class=\"col5\">66</td><td></td><td class=\"col6\">49</td></tr><tr><td class=\"col0\">2084</td><td></td><td class=\"col1\">14,140</td><td></td><td class=\"col2\">268</td><td></td><td class=\"col3\">3,006</td><td></td><td class=\"col4\">17,414</td><td></td><td class=\"col5\">67</td><td></td><td class=\"col6\">50</td></tr><tr><td class=\"col0\">2085</td><td></td><td class=\"col1\">14,246</td><td></td><td class=\"col2\">270</td><td></td><td class=\"col3\">3,020</td><td></td><td class=\"col4\">17,536</td><td></td><td class=\"col5\">67</td><td></td><td class=\"col6\">50</td></tr><tr><td class=\"col0\">2086</td><td></td><td class=\"col1\">14,339</td><td></td><td class=\"col2\">272</td><td></td><td class=\"col3\">3,034</td><td></td><td class=\"col4\">17,645</td><td></td><td class=\"col5\">67</td><td></td><td class=\"col6\">50</td></tr><tr><td class=\"col0\">2087</td><td></td><td class=\"col1\">14,420</td><td></td><td class=\"col2\">273</td><td></td><td class=\"col3\">3,049</td><td></td><td class=\"col4\">17,741</td><td></td><td class=\"col5\">67</td><td></td><td class=\"col6\">50</td></tr><tr><td class=\"col0\">2088</td><td></td><td class=\"col1\">14,488</td><td></td><td class=\"col2\">274</td><td></td><td class=\"col3\">3,064</td><td></td><td class=\"col4\">17,825</td><td></td><td class=\"col5\">67</td><td></td><td class=\"col6\">50</td></tr><tr><td class=\"col0\">2089</td><td></td><td class=\"col1\">14,545</td><td></td><td class=\"col2\">275</td><td></td><td class=\"col3\">3,079</td><td></td><td class=\"col4\">17,899</td><td></td><td class=\"col5\">67</td><td></td><td class=\"col6\">50</td></tr><tr><td class=\"col0\">2090</td><td></td><td class=\"col1\">14,594</td><td></td><td class=\"col2\">275</td><td></td><td class=\"col3\">3,094</td><td></td><td class=\"col4\">17,963</td><td></td><td class=\"col5\">67</td><td></td><td class=\"col6\">50</td></tr></tbody>", 
        "header": "<thead><tr><th class=\"series col0\" colspan=\"1\" rowspan=\"2\">Calendar year</th><td colspan=\"1\" rowspan=\"2\"></td><th class=\"series col1\" colspan=\"1\" rowspan=\"2\">Disabled-worker beneficiaries</th><td colspan=\"1\" rowspan=\"2\"></td><th class=\"series\" colspan=\"3\" rowspan=\"1\">Auxiliary beneficiaries</th><td colspan=\"1\" rowspan=\"2\"></td><th class=\"series col4\" colspan=\"1\" rowspan=\"2\">Total beneficiaries</th><td colspan=\"1\" rowspan=\"2\"></td><th class=\"series\" colspan=\"3\" rowspan=\"1\">Disability prevalence rates</th></tr><tr><th class=\"series col2\">Spouse</th><td></td><th class=\"series col3\">Child</th><th class=\"series col5\">Gross</th><td></td><th class=\"series col6\">Age-sex adjusted<span class=\"top_footnote top_a\">a</span></th></tr></thead>"
    }, 
    "title": {
        "id": "V_C5-1", 
        "name": "DI Beneficiaries with Benefits in Current-Payment Status at the End of Calendar Years 1975\u20132090 (Beneficiaries in thousands; prevalence rates per thousand persons insured for disability benefits) :: Subtable : Intermediate"
    }
}